{
    "perSecond": [
        {
            "avgPacketSize": 74.8,
            "bps": 374,
            "connections": [
                {
                    "dst": "34.160.144.191",
                    "src": "192.168.1.102"
                },
                {
                    "dst": "192.168.1.1",
                    "src": "192.168.1.102"
                },
                {
                    "dst": "192.168.1.102",
                    "src": "192.168.1.1"
                },
                {
                    "dst": "192.168.1.102",
                    "src": "34.160.144.191"
                }
            ],
            "pps": 5,
            "protocolCounts": {
                "ARP": 2,
                "TCP": 3
            },
            "second": 1
        }
    ],
    "sessionEnd": "2025-10-02T15:00:42",
    "sessionStart": "2025-10-02T15:00:41"
}
